pypisearch/__init__.py
pypisearch/__main__.py
pypisearch/main.py
pypisearch/re_constants.py
pypisearch/result_item.py
pypisearch/search.py
pypisearch-1.3.5.dist-info/LICENSE
pypisearch-1.3.5.dist-info/METADATA
pypisearch-1.3.5.dist-info/WHEEL
pypisearch-1.3.5.dist-info/entry_points.txt
pypisearch-1.3.5.dist-info/top_level.txt
pypisearch-1.3.5.dist-info/RECORD
