Metadata-Version: 2.1
Name: pypisearch
Version: 1.3.5
Summary: Replacement of temporarily deprecated pip search command
Home-page: https://github.com/shidenko97/pypisearch
Author: Serhii Hidenko
Author-email: shidenko97@gmail.com
License: UNKNOWN
Platform: UNKNOWN
Classifier: Programming Language :: Python :: 3
Classifier: License :: OSI Approved :: MIT License
Classifier: Operating System :: OS Independent
Requires-Python: >=3.8
Requires-Dist: certifi (==2020.12.5)
Requires-Dist: chardet (==4.0.0)
Requires-Dist: idna (==2.10)
Requires-Dist: requests (==2.25.1)
Requires-Dist: tabulate (==0.8.9)
